[
  {"mid": "1", "title": "prototype", "icon": "🍉", "pathname": "/prototype", "submenus": [
    {"mid": "11", "title": "fund", "icon": "", "pathname": "/prototype/fund/fund-mng"},
    {"mid": "12", "title": "mybatis", "icon": "", "pathname": "/prototype/mybatis", "submenus": [
      {"mid": "121", "title": "scientist", "icon": "", "pathname": "/prototype/mybatis/scientist/scientist-mng"}
    ]},
    {"mid": "13", "title": "jpa", "icon": "", "pathname": "/prototype/jpa", "submenus": [
      {"mid": "131", "title": "planet", "icon": "", "pathname": "/prototype/jpa/planet/planet-mng"},
      {"mid": "132", "title": "satellite", "icon": "", "pathname": "/prototype/jpa/satellite/satellite-mng"}
    ]},
    {"mid": "14", "title": "system", "icon": "", "pathname": "/prototype/system", "submenus": [
      {"mid": "141", "title": "code", "icon": "", "pathname": "/prototype/system/code-mng"},
      {"mid": "142", "title": "error log", "icon": "", "pathname": "/prototype/system/error-log"}
    ]}
  ]},
  {"mid": "2", "title": "docs", "icon": "🥕", "pathname": "/docs"}
]